hpc/__init__.py
hpc/indexing.py
hpc_utils-0.1.5.dist-info/licenses/LICENSE.md
hpc_utils-0.1.5.dist-info/METADATA
hpc_utils-0.1.5.dist-info/WHEEL
hpc_utils-0.1.5.dist-info/top_level.txt
hpc_utils-0.1.5.dist-info/RECORD
